amharicNLP/__init__.py
amharicNLP/example/__init__.py
amharicNLP/example/test.py
amharicNLP/resources/__init__.py
amharicNLP/resources/amharic_stopword.py
amharicNLP/resources/cleaner.py
amharicNLP/resources/data_lemma.py
amharicNLP/resources/lemmatizer.py
amharicNLP/resources/normalizer.py
amharicNLP/resources/stemmer.py
amharicNLP/resources/stopwrod.py
amharicNLP/resources/tokenizer.py
amharicNLP/resources/utils.py
amharicNLP/resources/tests/__init__.py
amharicNLP/resources/tests/conftest.py
amharicNLP/resources/tests/test_cleaner.py
amharicNLP/resources/tests/test_lemmatizer.py
amharicNLP/resources/tests/test_normalizer.py
amharicNLP/resources/tests/test_utils.py
amharicNLP/utilities/__init__.py
amharicNLP/utilities/data_augmenter.py
amharicNLP/wordnet/__init__.py
amharicnlp-0.8.0.dist-info/licenses/LICENSE
amharicnlp-0.8.0.dist-info/METADATA
amharicnlp-0.8.0.dist-info/WHEEL
amharicnlp-0.8.0.dist-info/top_level.txt
amharicnlp-0.8.0.dist-info/RECORD
