Metadata-Version: 2.4
Name: amharicNLP
Version: 0.8.0
Summary: amharicNLP is a Python package for Amharic Natural Language Processing (NLP) and text preprocessing. 
Author-email: Yonas Abebe <abebeyonas88@gmail.com>
License: MIT
Project-URL: Homepage, https://github.com/yonasab12/amharicNLP
Project-URL: Repository, https://github.com/yonasab12/amharicNLP
Keywords: Amharic,NLP,Amharic NLP,Amharic preprocessing,Amharic tokenizer,Amharic stopwords,Amharic sentiment analysis,Amharic text processing,Ethiopian NLP,tokenizer,normalizer,sentiment analysis,amharicnlp,amharicprocessing,amharicnltk,tokinization,amharicstopword
Classifier: Programming Language :: Python :: 3
Classifier: Operating System :: OS Independent
Classifier: Topic :: Text Processing :: Linguistic
Classifier: Natural Language :: English
Classifier: Intended Audience :: Developers
Classifier: License :: OSI Approved :: MIT License
Requires-Python: >=3.8
License-File: LICENSE
Requires-Dist: numpy
Requires-Dist: transformers
Requires-Dist: torch
Requires-Dist: regex
Dynamic: license-file
